planets/__init__.py
planets/planets.py
planets/tests.py
Planet_Objects-1.0.4.dist-info/LICENSE
Planet_Objects-1.0.4.dist-info/METADATA
Planet_Objects-1.0.4.dist-info/WHEEL
Planet_Objects-1.0.4.dist-info/top_level.txt
Planet_Objects-1.0.4.dist-info/RECORD
