Metadata-Version: 2.1
Name: Planet Objects
Version: 1.0.4
Summary: Planetary data stored as objects
Home-page: https://github.com/matthewkayne/Planets
Author: Matthew Kayne
Author-email: matthewkayne2004@gmail.com
License: UNKNOWN
Platform: UNKNOWN
License-File: LICENSE
